{"site": "CNN", "title": "CNN - Breaking News, Latest News and Videos", "url": "https://www.cnn.com", "main": {"headline": "Macron's surprise G7 invite sparks confusion", "sub": "An unexpected arrival at the summit made it appear as if the French president had pulled off an end run around his most powerful guest, President Trump", "link": "/2019/08/25/politics/g7-iran-zarif-france-intl/index.html"}, "headlines": [{"headline": "Something is rotten in Denmark", "link": "https://www.cnn.com/2019/08/25/opinions/call-him-king-trump-opinion-weekly-column-carr/index.html"}, {"headline": "Dow futures slide Sunday night amid swirl of confusing signals on trade", "link": "https://www.cnn.com/2019/08/25/intl_business/asian-market-latest/index.html"}, {"headline": "Giant pumice stone in the Pacific could help heal Great Barrier Reef", "link": "https://www.cnn.com/2019/08/25/asia/pumice-stone-underwater-volcano-great-barrier-reef-intl/index.html"}]}